lazy_property/__init__.py
property_lazy-0.0.10.dist-info/LICENSE
property_lazy-0.0.10.dist-info/METADATA
property_lazy-0.0.10.dist-info/WHEEL
property_lazy-0.0.10.dist-info/top_level.txt
property_lazy-0.0.10.dist-info/RECORD
