Metadata-Version: 2.1
Name: property_lazy
Version: 0.0.10
Summary: Makes properties lazy (ie evaluated only when called)
Home-page: https://github.com/maiyajj/property_lazy.git
Author: maiyajj
Author-email: 1045373828@qq.com
License: MIT
License-File: LICENSE
